gitflow_authors_linter/__init__.py
gitflow_authors_linter-0.0.2.dist-info/LICENSE
gitflow_authors_linter-0.0.2.dist-info/METADATA
gitflow_authors_linter-0.0.2.dist-info/WHEEL
gitflow_authors_linter-0.0.2.dist-info/top_level.txt
gitflow_authors_linter-0.0.2.dist-info/RECORD
