Metadata-Version: 2.1
Name: gitflow-authors-linter
Version: 0.0.2
Summary: Provides additional functionality to gitflow-linter tool
Home-page: https://github.com/fighterpoul/gitflow_authors_linter
Author: Poul Fighter
Author-email: fighter.poul@gmail.com
License: MIT
Platform: UNKNOWN
Classifier: License :: OSI Approved :: MIT License
Classifier: Programming Language :: Python :: 3.8
Requires-Python: >3.8
Requires-Dist: PyYAML (>=5.4.1)
Requires-Dist: GitPython (>=3.1.17)
Requires-Dist: click (>=7)
Requires-Dist: gitflow-linter (>=0.0.4)
